{
  "SECTOR 11": {
    "valor": 2.71,
    "timestamp": "28-01-2026 07:25",
    "rssi": "-66"
  },
  "SECTOR 12": {
    "valor": 1.96,
    "timestamp": "28-01-2026 07:25",
    "rssi": "-66"
  },
  "SECTOR 13": {
    "valor": 1.95,
    "timestamp": "28-01-2026 07:25",
    "rssi": "-66"
  },
  "SECTOR 13 CHOYAL": {
    "valor": 2.18,
    "timestamp": "28-01-2026 07:25",
    "rssi": "-66"
  },
  "SECTOR 14": {
    "valor": 3.0,
    "timestamp": "28-01-2026 07:25",
    "rssi": "-66"
  },
  "SECTOR 15": {
    "valor": 2.23,
    "timestamp": "28-01-2026 07:25",
    "rssi": "-66"
  },
  "SECTOR 16": {
    "valor": 0.74,
    "timestamp": "28-01-2026 07:25",
    "rssi": "-66"
  },
  "SECTOR 17": {
    "valor": 1.68,
    "timestamp": "28-01-2026 07:25",
    "rssi": "-66"
  },
  "SECTOR 18": {
    "valor": 2.81,
    "timestamp": "28-01-2026 07:25",
    "rssi": "-66"
  },
  "SECTOR 19": {
    "valor": 1.79,
    "timestamp": "28-01-2026 07:25",
    "rssi": "-66"
  },
  "SECTOR 10": {
    "valor": 0.0,
    "timestamp": "28-01-2026 07:27",
    "rssi": -117
  },
  "SECTOR 4": {
    "valor": 0.0,
    "timestamp": "27-01-2026 08:45",
    "rssi": -106
  },
  "SECTOR 8": {
    "valor": 0.0,
    "timestamp": "28-01-2026 07:22",
    "rssi": -118
  },
  "SECTOR 5": {
    "valor": 0.0,
    "timestamp": "28-01-2026 07:26",
    "rssi": -113
  }
}