{
  "SECTOR 11": {
    "valor": 1.65,
    "timestamp": "19-03-2026 00:30",
    "rssi": "-68"
  },
  "SECTOR 12": {
    "valor": 1.73,
    "timestamp": "19-03-2026 00:30",
    "rssi": "-68"
  },
  "SECTOR 13": {
    "valor": 1.44,
    "timestamp": "19-03-2026 00:30",
    "rssi": "-68"
  },
  "SECTOR 13 CHOYAL": {
    "valor": 2.22,
    "timestamp": "19-03-2026 00:30",
    "rssi": "-68"
  },
  "SECTOR 14": {
    "valor": 1.77,
    "timestamp": "19-03-2026 00:30",
    "rssi": "-68"
  },
  "SECTOR 15": {
    "valor": 0.7,
    "timestamp": "19-03-2026 00:30",
    "rssi": "-68"
  },
  "SECTOR 16": {
    "valor": 2.79,
    "timestamp": "19-03-2026 00:30",
    "rssi": "-68"
  },
  "SECTOR 17": {
    "valor": 1.22,
    "timestamp": "19-03-2026 00:30",
    "rssi": "-68"
  },
  "SECTOR 18": {
    "valor": 1.34,
    "timestamp": "19-03-2026 00:30",
    "rssi": "-68"
  },
  "SECTOR 19": {
    "valor": 1.56,
    "timestamp": "19-03-2026 00:30",
    "rssi": "-68"
  },
  "SECTOR 8": {
    "valor": 0.0,
    "timestamp": "19-03-2026 00:31",
    "rssi": -115
  },
  "SECTOR 5": {
    "valor": 0.0,
    "timestamp": "19-03-2026 00:22",
    "rssi": -113
  },
  "SECTOR 10": {
    "valor": 0.0,
    "timestamp": "19-03-2026 00:34",
    "rssi": -117
  }
}