{
  "SECTOR 11": {
    "valor": 2.78,
    "timestamp": "13-03-2026 17:07",
    "rssi": "-73"
  },
  "SECTOR 12": {
    "valor": 1.85,
    "timestamp": "13-03-2026 17:07",
    "rssi": "-73"
  },
  "SECTOR 13": {
    "valor": 3.0,
    "timestamp": "13-03-2026 17:07",
    "rssi": "-73"
  },
  "SECTOR 13 CHOYAL": {
    "valor": 0.5,
    "timestamp": "13-03-2026 17:07",
    "rssi": "-73"
  },
  "SECTOR 14": {
    "valor": 1.66,
    "timestamp": "13-03-2026 17:07",
    "rssi": "-73"
  },
  "SECTOR 15": {
    "valor": 1.31,
    "timestamp": "13-03-2026 17:07",
    "rssi": "-73"
  },
  "SECTOR 16": {
    "valor": 2.31,
    "timestamp": "13-03-2026 17:07",
    "rssi": "-73"
  },
  "SECTOR 17": {
    "valor": 1.61,
    "timestamp": "13-03-2026 17:07",
    "rssi": "-73"
  },
  "SECTOR 18": {
    "valor": 2.93,
    "timestamp": "13-03-2026 17:07",
    "rssi": "-73"
  },
  "SECTOR 19": {
    "valor": 1.27,
    "timestamp": "13-03-2026 17:07",
    "rssi": "-73"
  },
  "SECTOR 8": {
    "valor": 0.0,
    "timestamp": "13-03-2026 17:11",
    "rssi": -118
  },
  "SECTOR 5": {
    "valor": 0.0,
    "timestamp": "13-03-2026 17:11",
    "rssi": -111
  },
  "SECTOR 10": {
    "valor": 0.0,
    "timestamp": "13-03-2026 17:13",
    "rssi": -118
  }
}