{
  "SECTOR 11": {
    "valor": 2.77,
    "timestamp": "24-01-2026 11:06",
    "rssi": "-77"
  },
  "SECTOR 12": {
    "valor": 2.14,
    "timestamp": "24-01-2026 11:06",
    "rssi": "-77"
  },
  "SECTOR 13": {
    "valor": 1.98,
    "timestamp": "24-01-2026 11:06",
    "rssi": "-77"
  },
  "SECTOR 13 CHOYAL": {
    "valor": 1.74,
    "timestamp": "24-01-2026 11:06",
    "rssi": "-77"
  },
  "SECTOR 14": {
    "valor": 2.75,
    "timestamp": "24-01-2026 11:06",
    "rssi": "-77"
  },
  "SECTOR 15": {
    "valor": 2.63,
    "timestamp": "24-01-2026 11:06",
    "rssi": "-77"
  },
  "SECTOR 16": {
    "valor": 0.88,
    "timestamp": "24-01-2026 11:06",
    "rssi": "-77"
  },
  "SECTOR 17": {
    "valor": 1.5,
    "timestamp": "24-01-2026 11:06",
    "rssi": "-77"
  },
  "SECTOR 18": {
    "valor": 2.85,
    "timestamp": "24-01-2026 11:06",
    "rssi": "-77"
  },
  "SECTOR 19": {
    "valor": 2.3,
    "timestamp": "24-01-2026 11:06",
    "rssi": "-77"
  },
  "SECTOR 10": {
    "valor": 0.0,
    "timestamp": "24-01-2026 11:12",
    "rssi": -117
  },
  "SECTOR 4": {
    "valor": 0.0,
    "timestamp": "24-01-2026 11:11",
    "rssi": -107
  },
  "SECTOR 8": {
    "valor": 0.0,
    "timestamp": "24-01-2026 11:11",
    "rssi": -119
  },
  "SECTOR 5": {
    "valor": 0.0,
    "timestamp": "24-01-2026 11:10",
    "rssi": -113
  }
}