{
  "SECTOR 11": {
    "valor": 1.72,
    "timestamp": "08-02-2026 22:04",
    "rssi": "-67"
  },
  "SECTOR 12": {
    "valor": 0.9,
    "timestamp": "08-02-2026 22:04",
    "rssi": "-67"
  },
  "SECTOR 13": {
    "valor": 0.94,
    "timestamp": "08-02-2026 22:04",
    "rssi": "-67"
  },
  "SECTOR 13 CHOYAL": {
    "valor": 1.3,
    "timestamp": "08-02-2026 22:04",
    "rssi": "-67"
  },
  "SECTOR 14": {
    "valor": 1.93,
    "timestamp": "08-02-2026 22:04",
    "rssi": "-67"
  },
  "SECTOR 15": {
    "valor": 2.77,
    "timestamp": "08-02-2026 22:04",
    "rssi": "-67"
  },
  "SECTOR 16": {
    "valor": 0.5,
    "timestamp": "08-02-2026 22:04",
    "rssi": "-67"
  },
  "SECTOR 17": {
    "valor": 0.97,
    "timestamp": "08-02-2026 22:04",
    "rssi": "-67"
  },
  "SECTOR 18": {
    "valor": 1.52,
    "timestamp": "08-02-2026 22:04",
    "rssi": "-67"
  },
  "SECTOR 19": {
    "valor": 3.0,
    "timestamp": "08-02-2026 22:04",
    "rssi": "-67"
  },
  "SECTOR 10": {
    "valor": 0.0,
    "timestamp": "08-02-2026 22:09",
    "rssi": -117
  },
  "SECTOR 4": {
    "valor": 0.0,
    "timestamp": "27-01-2026 08:45",
    "rssi": -106
  },
  "SECTOR 8": {
    "valor": 0.0,
    "timestamp": "08-02-2026 22:11",
    "rssi": -114
  },
  "SECTOR 5": {
    "valor": 0.0,
    "timestamp": "08-02-2026 22:07",
    "rssi": -115
  }
}